tg_notifier/__init__.py
tg_notifier-0.1.0.dist-info/METADATA
tg_notifier-0.1.0.dist-info/WHEEL
tg_notifier-0.1.0.dist-info/top_level.txt
tg_notifier-0.1.0.dist-info/RECORD
