Metadata-Version: 2.4
Name: tg_notifier
Version: 0.1.0
Summary: отправка уведомлений в телеграм без зависимостей
Home-page: https://github.com/imbecility/tg_notifier
Author: imbecility
Requires-Python: >=3.10
Requires-Dist: setuptools>=80.9.0
Dynamic: author
Dynamic: home-page
Dynamic: requires-python
